<?xml version="1.0" encoding="UTF-8"?>
<!-- minLevel -> Lowest level encounter for that mob. -->
<!-- maxLevel -> Highest level encounter for that mob. -->
<!-- area -> area by id found in areas.xml where that mob can appear. To add additional areas to
     a mob, simply add another <area id=""></area> tag below the existing ones for the mob. -->
<enemies>
 <!-- Mines of Glooming Deep (1-9) -->
  <enemy id="1" name="a cave bat" minLevel="1" maxLevel="1" HP="100" ATK="6" DEF="5" MR="0" xp="100">
    <areas>
      <area id="1"/>
    </areas>
  </enemy>
  <enemy id="2" name="a cave rat" minLevel="2" maxLevel="2" HP="105" ATK="7" DEF="6" MR="0" xp="150">
    <areas>
      <area id="1"/>
    </areas>
  </enemy>
  <enemy id="3" name="a dark elf slave" minLevel="3" maxLevel="3" HP="110" ATK="8" DEF="7" MR="0" xp="200">
    <areas>
      <area id="1"/>
    </areas>
  </enemy>
  <enemy id="4" name="a gloomfang lurker" minLevel="4" maxLevel="4" HP="116" ATK="9" DEF="8" MR="0" xp="250">
    <areas>
      <area id="1"/>
    </areas>
  </enemy>
  <enemy id="5" name="a goblin slave" minLevel="5" maxLevel="5" HP="122" ATK="10" DEF="9" MR="0" xp="300">
    <areas>
      <area id="1"/>
    </areas>
  </enemy>
  <enemy id="6" name="a garroted kobold" minLevel="6" maxLevel="8" HP="128" ATK="11" DEF="10" MR="0" xp="350">
    <areas>
      <area id="1"/>
    </areas>
  </enemy>
  <enemy id="7" name="a Gloomingdeep captain" minLevel="7" maxLevel="9" HP="135" ATK="12" DEF="11" MR="10" xp="400">
    <areas>
      <area id="1"/>
    </areas>
  </enemy>
  <enemy id="8" name="a trampled kobold" minLevel="7" maxLevel="7" HP="135" ATK="12" DEF="11" MR="0" xp="400">
    <areas>
      <area id="1"/>
    </areas>
  </enemy>
  <enemy id="9" name="Slavemaster Ruga" minLevel="8" maxLevel="8" HP="142" ATK="13" DEF="12" MR="15" xp="450">
    <areas>
      <area id="1"/>
    </areas>
  </enemy>
  <enemy id="10" name="Gloomingdeep Spiritweaver" minLevel="8" maxLevel="8" HP="142" ATK="13" DEF="12" MR="0" xp="450">
    <areas>
      <area id="1"/>
    </areas>
  </enemy>
  <enemy id="11" name="Pox" minLevel="9" maxLevel="9" HP="149" ATK="14" DEF="13" MR="10" xp="500">
    <areas>
      <area id="1"/>
    </areas>
  </enemy>
  <!-- Innothule Swamp (2-12) -->
  <enemy id="12" name="a froglok" minLevel="2" maxLevel="4" HP="105" ATK="7" DEF="6" MR="0" xp="150">
    <areas>
      <area id="2"/>
    </areas>
  </enemy>
  <enemy id="13" name="a giant rat" minLevel="2" maxLevel="4" HP="105" ATK="7" DEF="6" MR="0" xp="150">
    <areas>
      <area id="2"/>
    </areas>
  </enemy>
  <enemy id="14" name="a kobold" minLevel="3" maxLevel="5" HP="110" ATK="8" DEF="7" MR="0" xp="200">
    <areas>
      <area id="2"/>
    </areas>
  </enemy>
  <enemy id="15" name="a swamp alligator" minLevel="3" maxLevel="5" HP="110" ATK="8" DEF="7" MR="0" xp="200">
    <areas>
      <area id="2"/>
    </areas>
  </enemy>
  <enemy id="16" name="a water moccasin" minLevel="4" maxLevel="6" HP="116" ATK="9" DEF="8" MR="0" xp="250">
    <areas>
      <area id="2"/>
    </areas>
  </enemy>
  <enemy id="17" name="an alligator" minLevel="4" maxLevel="6" HP="116" ATK="9" DEF="8" MR="0" xp="250">
    <areas>
      <area id="2"/>
    </areas>
  </enemy>
  <enemy id="18" name="a fungal watcher" minLevel="5" maxLevel="5" HP="122" ATK="10" DEF="9" MR="0" xp="300">
    <areas>
      <area id="2"/>
    </areas>
  </enemy>
  <enemy id="19" name="a fetid froglok ghoul" minLevel="5" maxLevel="7" HP="122" ATK="10" DEF="9" MR="0" xp="300">
    <areas>
      <area id="2"/>
    </areas>
  </enemy>
  <enemy id="20" name="a froglok forager" minLevel="5" maxLevel="7" HP="122" ATK="10" DEF="9" MR="0" xp="300">
    <areas>
      <area id="2"/>
    </areas>
  </enemy>
  <enemy id="21" name="a kobold hunter" minLevel="6" maxLevel="8" HP="128" ATK="11" DEF="10" MR="0" xp="350">
    <areas>
      <area id="2"/>
    </areas>
  </enemy>
  <enemy id="22" name="a froglok ghoul" minLevel="8" maxLevel="10" HP="142" ATK="13" DEF="12" MR="10" xp="450">
    <areas>
      <area id="2"/>
    </areas>
  </enemy>
  <enemy id="23" name="a fat alligator" minLevel="9" maxLevel="10" HP="149" ATK="14" DEF="13" MR="0" xp="500">
    <areas>
      <area id="2"/>
    </areas>
  </enemy>
  <enemy id="24" name="a Large Forest Crawler" minLevel="10" maxLevel="12" HP="157" ATK="15" DEF="14" MR="0" xp="550">
    <areas>
      <area id="2"/>
    </areas>
  </enemy>
  <enemy id="25" name="a lesser mummy" minLevel="10" maxLevel="12" HP="157" ATK="15" DEF="14" MR="0" xp="550">
    <areas>
      <area id="2"/>
    </areas>
  </enemy>
  <!-- Blackburrow (2-15) -->
  <enemy id="26" name="a gnoll scout" minLevel="2" maxLevel="2" HP="105" ATK="7" DEF="6" MR="0" xp="150">
    <areas>
      <area id="3"/>
    </areas>
  </enemy>
  <enemy id="27" name="a brown bear" minLevel="3" maxLevel="3" HP="110" ATK="8" DEF="7" MR="0" xp="200">
    <areas>
      <area id="3"/>
    </areas>
  </enemy>
  <enemy id="28" name="a scrawny gnoll" minLevel="3" maxLevel="5" HP="110" ATK="8" DEF="7" MR="0" xp="200">
    <areas>
      <area id="3"/>
    </areas>
  </enemy>
  <enemy id="29" name="a razorgill" minLevel="4" maxLevel="8" HP="116" ATK="9" DEF="8" MR="0" xp="250">
    <areas>
      <area id="3"/>
    </areas>
  </enemy>
  <enemy id="30" name="a gnoll" minLevel="5" maxLevel="7" HP="122" ATK="10" DEF="9" MR="0" xp="300">
    <areas>
      <area id="3"/>
    </areas>
  </enemy>
  <enemy id="31" name="a gnoll guardsman" minLevel="5" maxLevel="7" HP="122" ATK="10" DEF="9" MR="0" xp="300">
    <areas>
      <area id="3"/>
    </areas>
  </enemy>
  <enemy id="32" name="a burly gnoll" minLevel="7" maxLevel="9" HP="135" ATK="12" DEF="11" MR="0" xp="400">
    <areas>
      <area id="3"/>
    </areas>
  </enemy>
  <enemy id="33" name="a giant snake" minLevel="7" maxLevel="11" HP="135" ATK="12" DEF="11" MR="0" xp="400">
    <areas>
      <area id="3"/>
    </areas>
  </enemy>
  <enemy id="34" name="a grizzly bear" minLevel="9" maxLevel="11" HP="149" ATK="14" DEF="13" MR="0" xp="500">
    <areas>
      <area id="3"/>
    </areas>
  </enemy>
  <enemy id="35" name="an elite gnoll guard" minLevel="11" maxLevel="15" HP="165" ATK="16" DEF="15" MR="0" xp="600">
    <areas>
      <area id="3"/>
    </areas>
  </enemy>
  <enemy id="36" name="a gnoll commander" minLevel="14" maxLevel="15" HP="193" ATK="19" DEF="18" MR="15" xp="750">
    <areas>
      <area id="3"/>
    </areas>
  </enemy>
  <!-- Field of Bone (2-20) -->
  <enemy id="37" name="a carrion beetle hatchling" minLevel="2" maxLevel="3" HP="105" ATK="7" DEF="6" MR="0" xp="150">
    <areas>
      <area id="4"/>
    </areas>
  </enemy>
  <enemy id="38" name="a scaled wolf cub" minLevel="2" maxLevel="4" HP="105" ATK="7" DEF="6" MR="0" xp="150">
    <areas>
      <area id="4"/>
    </areas>
  </enemy>
  <enemy id="39" name="a scaled wolf" minLevel="5" maxLevel="5" HP="122" ATK="10" DEF="9" MR="0" xp="300">
    <areas>
      <area id="4"/>
    </areas>
  </enemy>
  <enemy id="40" name="a large scorpion" minLevel="4" maxLevel="6" HP="116" ATK="9" DEF="8" MR="0" xp="250">
    <areas>
      <area id="4"/>
    </areas>
  </enemy>
  <enemy id="41" name="a militia skeleton" minLevel="5" maxLevel="6" HP="122" ATK="10" DEF="9" MR="0" xp="300">
    <areas>
      <area id="4"/>
    </areas>
  </enemy>
  <enemy id="42" name="a scalebone skeleton" minLevel="7" maxLevel="9" HP="135" ATK="12" DEF="11" MR="0" xp="400">
    <areas>
      <area id="4"/>
    </areas>
  </enemy>
  <enemy id="43" name="a giant scorpion" minLevel="8" maxLevel="10" HP="142" ATK="13" DEF="12" MR="0" xp="450">
    <areas>
      <area id="4"/>
    </areas>
  </enemy>
  <enemy id="44" name="a scaled wolf hunter" minLevel="9" maxLevel="11" HP="149" ATK="14" DEF="13" MR="0" xp="500">
    <areas>
      <area id="4"/>
    </areas>
  </enemy>
  <enemy id="45" name="a burynai burrower" minLevel="10" maxLevel="12" HP="157" ATK="15" DEF="14" MR="0" xp="550">
    <areas>
      <area id="4"/>
    </areas>
  </enemy>
  <enemy id="46" name="a bonebinder" minLevel="12" maxLevel="14" HP="174" ATK="17" DEF="16" MR="0" xp="650">
    <areas>
      <area id="4"/>
    </areas>
  </enemy>
  <enemy id="47" name="a burynai excavator" minLevel="13" maxLevel="15" HP="183" ATK="18" DEF="17" MR="0" xp="700">
    <areas>
      <area id="4"/>
    </areas>
  </enemy>
  <enemy id="48" name="a heartsting scorpion" minLevel="12" maxLevel="14" HP="174" ATK="17" DEF="16" MR="0" xp="650">
    <areas>
      <area id="4"/>
    </areas>
  </enemy>
  <enemy id="49" name="a large heartsting scorpion" minLevel="15" maxLevel="17" HP="203" ATK="20" DEF="19" MR="0" xp="800">
    <areas>
      <area id="4"/>
    </areas>
  </enemy>
  <enemy id="50" name="a burynai sapper" minLevel="16" maxLevel="17" HP="214" ATK="21" DEF="20" MR="0" xp="850">
    <areas>
      <area id="4"/>
    </areas>
  </enemy>
  <enemy id="51" name="a lesser icebone skeleton" minLevel="16" maxLevel="18" HP="214" ATK="21" DEF="20" MR="15" xp="850">
    <areas>
      <area id="4"/>
    </areas>
  </enemy>
  <enemy id="52" name="a scaled wolf tracker" minLevel="19" maxLevel="19" HP="249" ATK="24" DEF="23" MR="0" xp="1000">
    <areas>
      <area id="4"/>
    </areas>
  </enemy>
  <enemy id="53" name="a burynai cutter" minLevel="20" maxLevel="20" HP="262" ATK="25" DEF="24" MR="0" xp="1050">
    <areas>
      <area id="4"/>
    </areas>
  </enemy>
  <enemy id="54" name="a scaled wolf prowler" minLevel="19" maxLevel="20" HP="249" ATK="24" DEF="23" MR="0" xp="1000">
    <areas>
      <area id="4"/>
    </areas>
  </enemy>
  <!-- Nektulos Forest (5-20) -->
  <enemy id="55" name="a black bear" minLevel="5" maxLevel="5" HP="122" ATK="10" DEF="9" MR="0" xp="300">
    <areas>
      <area id="5"/>
    </areas>
  </enemy>
  <enemy id="56" name="a skeleton" minLevel="5" maxLevel="5" HP="122" ATK="10" DEF="9" MR="0" xp="300">
    <areas>
      <area id="5"/>
    </areas>
  </enemy>
  <enemy id="57" name="a calcified skeleton" minLevel="5" maxLevel="6" HP="122" ATK="10" DEF="9" MR="0" xp="300">
    <areas>
      <area id="5"/>
    </areas>
  </enemy>
  <enemy id="58" name="a leatherfoot skeleton" minLevel="5" maxLevel="6" HP="122" ATK="10" DEF="9" MR="0" xp="300">
    <areas>
      <area id="5"/>
    </areas>
  </enemy>
  <enemy id="59" name="a black mamba" minLevel="7" maxLevel="9" HP="135" ATK="12" DEF="11" MR="0" xp="400">
    <areas>
      <area id="5"/>
    </areas>
  </enemy>
  <enemy id="60" name="a greater skeleton" minLevel="7" maxLevel="9" HP="135" ATK="12" DEF="11" MR="0" xp="400">
    <areas>
      <area id="5"/>
    </areas>
  </enemy>
  <enemy id="61" name="a halfling skeleton" minLevel="7" maxLevel="8" HP="135" ATK="12" DEF="11" MR="0" xp="400">
    <areas>
      <area id="5"/>
    </areas>
  </enemy>
  <enemy id="62" name="a deathfist legionnaire" minLevel="7" maxLevel="9" HP="135" ATK="12" DEF="11" MR="0" xp="400">
    <areas>
      <area id="5"/>
    </areas>
  </enemy>
  <enemy id="63" name="a deathfist templar" minLevel="8" maxLevel="9" HP="142" ATK="13" DEF="12" MR="10" xp="450">
    <areas>
      <area id="5"/>
    </areas>
  </enemy>
  <enemy id="64" name="a large Piranha" minLevel="10" maxLevel="14" HP="157" ATK="15" DEF="14" MR="0" xp="550">
    <areas>
      <area id="5"/>
    </areas>
  </enemy>
  <enemy id="65" name="a lesser mummy" minLevel="10" maxLevel="12" HP="157" ATK="15" DEF="14" MR="0" xp="550">
    <areas>
      <area id="5"/>
    </areas>
  </enemy>
  <enemy id="66" name="a Nektulos widow" minLevel="10" maxLevel="12" HP="157" ATK="15" DEF="14" MR="0" xp="550">
    <areas>
      <area id="5"/>
    </areas>
  </enemy>
  <enemy id="67" name="a rotting citizen" minLevel="9" maxLevel="10" HP="149" ATK="14" DEF="13" MR="0" xp="500">
    <areas>
      <area id="5"/>
    </areas>
  </enemy>
  <enemy id="68" name="a willowisp" minLevel="9" maxLevel="11" HP="149" ATK="14" DEF="13" MR="0" xp="500">
    <areas>
      <area id="5"/>
    </areas>
  </enemy>
  <enemy id="69" name="a darkwater piranha" minLevel="11" maxLevel="15" HP="165" ATK="16" DEF="15" MR="0" xp="600">
    <areas>
      <area id="5"/>
    </areas>
  </enemy>
  <enemy id="70" name="a greater wisp" minLevel="11" maxLevel="13" HP="165" ATK="16" DEF="15" MR="0" xp="600">
    <areas>
      <area id="5"/>
    </areas>
  </enemy>
  <enemy id="71" name="a shadowed man pet" minLevel="16" maxLevel="18" HP="214" ATK="21" DEF="20" MR="0" xp="850">
    <areas>
      <area id="5"/>
    </areas>
  </enemy>
  <enemy id="72" name="a Guard D'Zel" minLevel="16" maxLevel="20" HP="214" ATK="21" DEF="20" MR="10" xp="850">
    <areas>
      <area id="5"/>
    </areas>
  </enemy>
  <enemy id="73" name="a Guard T'Aba" minLevel="16" maxLevel="20" HP="214" ATK="21" DEF="20" MR="10" xp="850">
    <areas>
      <area id="5"/>
    </areas>
  </enemy>
  <enemy id="74" name="a Guard V'Lex" minLevel="16" maxLevel="20" HP="214" ATK="21" DEF="20" MR="10" xp="850">
    <areas>
      <area id="5"/>
    </areas>
  </enemy>
  <enemy id="75" name="a Leatherfoot Medic" minLevel="19" maxLevel="20" HP="249" ATK="24" DEF="23" MR="0" xp="1000">
    <areas>
      <area id="5"/>
    </areas>
  </enemy>
  <!-- Crushbone (5-20) -->
  <!-- Befallen (5-20) -->
  <!-- Kurn's Tower (8-30) -->
  <!-- Upper Guk (10-30) -->
  <!-- Estate of Unrest (10-35) -->
  <!-- Temple of Solusek Ro (12-30) -->
  <!-- West Karana (10-35) -->
  <!-- East Karana (10-35) -->
  <!-- Kithicor Forest (15-40) -->
  <!-- The Overthere (15-40) -->
  <!-- Timorous Deep (15-50) -->
  <!-- Infected Paw (12-37) -->
  <!-- Castle Mistmoore (18-40) -->
  <!-- Najena (20-35) -->
  <!-- Crystal Caverns (25-45) -->
  <!-- Kedge Keep (35-50) -->
  <!-- Burning Woods (35-50) -->
  <!-- Great Divide (30-50) -->
  <!-- Lower Guk (30-50) -->
  <!-- Kaesora (30-50) -->
  <!-- City of Mist (35-53) -->
  <!-- Trakanon's Teeth (30-50) -->
  <!-- Tower of Frozen Shadow (30-55) -->
  <!-- Nagafen's Lair (40-55) -->
  <!-- Kael Drakkel (40-60) -->
  <!-- Skyshrine (40-60) -->
  <!-- Chardok (40-60) -->
  <!-- Old Sebilis (43-60) -->
  <!-- Howling Stones (40-60) -->
  <!-- Dragon Necropolis (45-60) -->
  <!-- Plane of Fear (46-65) -->
  <!-- Plane of Hate (46-65) -->
  <!-- Plane of Sky (46-65) -->
  <!-- Plane of Growth (46-60) -->
  <!-- Temple of Veeshan (46-65) -->
  <!-- Veeshan's Peak (60-75) -->
  <!-- Kerafyrm's Lair (60-75) -->
  <!-- Plane of Mischief (60-80) -->
  <!-- Argath, Bastion of Illdaera (85-100) -->
  <!-- Valley of Lunanyn (90-95) -->
  <!-- Sarith, City of Tides (90-95) -->
  <!-- Sepulcher East (95-100) -->
  <!-- Sepulcher West (95-100) -->
</enemies>
